fdnutil/__init__.py
fdnutil/bot.py
fdnutil/config.py
fdnutil/cypher.py
fdnutil/input.py
fdnutil/log.py
fdnutil/test_util.py
fdnutil/whoami.py
fdnutil-0.0.4.dist-info/LICENSE
fdnutil-0.0.4.dist-info/METADATA
fdnutil-0.0.4.dist-info/WHEEL
fdnutil-0.0.4.dist-info/top_level.txt
fdnutil-0.0.4.dist-info/RECORD
